paraloop/__init__.py
paraloop/aggregation_strategies.py
paraloop/paraloop.py
paraloop/syntax.py
paraloop/variable.py
paraloop/worker.py
paraloop-0.0.1.dev1.dist-info/LICENSE
paraloop-0.0.1.dev1.dist-info/METADATA
paraloop-0.0.1.dev1.dist-info/WHEEL
paraloop-0.0.1.dev1.dist-info/top_level.txt
paraloop-0.0.1.dev1.dist-info/RECORD
