Metadata-Version: 2.1
Name: paraloop
Version: 0.0.1.dev1
Summary: Simple Python for-loop parallelization
Home-page: UNKNOWN
Author: Jelmer Neeven
Author-email: jelmer@neeven.tech
License: MIT
Keywords: for loop parallel multiprocess python
Platform: Linux
Classifier: License :: OSI Approved :: MIT License
Classifier: Intended Audience :: Developers
Classifier: Operating System :: Unix
Classifier: Programming Language :: Python
Classifier: Programming Language :: Python :: 3.8
Classifier: Programming Language :: Python :: 3.9
Classifier: Topic :: Software Development :: Libraries :: Python Modules
Requires-Dist: numpy (>=1.17)
Provides-Extra: dev
Requires-Dist: black (==20.8b1) ; extra == 'dev'
Requires-Dist: docformatter (==1.4) ; extra == 'dev'
Requires-Dist: flake8 (==3.8.4) ; extra == 'dev'
Requires-Dist: isort (==5.7.0) ; extra == 'dev'
Requires-Dist: pytest (==6.2.2) ; extra == 'dev'
Requires-Dist: pytest-xdist (==2.2.1) ; extra == 'dev'
Requires-Dist: pytype (==2021.3.3) ; extra == 'dev'
